Myvoicerecognition/__init__.py
Myvoicerecognition-1.dist-info/LICENSE.md
Myvoicerecognition-1.dist-info/LICENSE.txt
Myvoicerecognition-1.dist-info/METADATA
Myvoicerecognition-1.dist-info/WHEEL
Myvoicerecognition-1.dist-info/top_level.txt
Myvoicerecognition-1.dist-info/RECORD
