Metadata-Version: 2.1
Name: Myvoicerecognition
Version: 1
Summary: a speech recognition system structured based on an acoustic and a language model
Home-page: https://github.com/Shahabks/Myvoicerecognition
Author: Shahab Sabahi
Author-email: sabahi.s@mysol-gc.jp
License: MIT
Keywords: praat speech signal processing phonetics
Platform: UNKNOWN
Classifier: Intended Audience :: Developers
Classifier: Intended Audience :: Science/Research
Classifier: Programming Language :: Python
Classifier: Programming Language :: Python :: 3.7
Requires-Dist: numpy (>=1.15.2)
Requires-Dist: SpeechRecognition (>=3.8.1)
Requires-Dist: pandas (>=0.23.4)
Requires-Dist: scipy (>=1.1.0)
